{
  "schema_version": 1,
  "target_codes": [
    "C18:2N6C",
    "C18:1N9C",
    "C18:3N3",
    "C20:4N6",
    "C20:5",
    "C20:3N8",
    "C22:6",
    "C22:5",
    "C22:4"
  ],
  "global": {
    "n_rows": 1350,
    "n_samples": 150
  },
  "targets": {
    "C18:2N6C": {
      "rt": {
        "n": 150,
        "median": 7.581833333333334,
        "mean": 7.582637777777777,
        "std": 0.00311553732757377,
        "q25": 7.580666666666667,
        "q75": 7.583583333333333,
        "robust_scale": 0.002223900000000084
      },
      "width": {
        "n": 150,
        "median": 0.0340000000000006,
        "mean": 0.0347733333333334,
        "std": 0.0020030791112499316,
        "q25": 0.0339999999999989,
        "q75": 0.0346666666666664,
        "robust_scale": 0.0020030791112499316
      },
      "left_width": {
        "n": 150,
        "median": 0.01766666666666645,
        "mean": 0.01831555555555565,
        "std": 0.0027653374763352365,
        "q25": 0.0173333333333332,
        "q75": 0.0179999999999997,
        "robust_scale": 0.0027653374763352365
      },
      "right_width": {
        "n": 150,
        "median": 0.0166666666666666,
        "mean": 0.016457777777777717,
        "std": 0.0011310740007009171,
        "q25": 0.016333333333333026,
        "q75": 0.0166666666666666,
        "robust_scale": 0.002
      },
      "chi2_like_rt_mean": 2.093462678029657,
      "chi2_like_width_mean": 1.1490518107164056,
      "status_top": {
        "matched_rt_baseexpand": 127,
        "matched_rt_valley": 19,
        "matched_rt_valley_baseexpand": 3,
        "matched_c18_local_bounds_valley": 1
      }
    },
    "C18:1N9C": {
      "rt": {
        "n": 150,
        "median": 7.614833333333333,
        "mean": 7.615382222222224,
        "std": 0.002394557615268295,
        "q25": 7.6137500000000005,
        "q75": 7.616666666666666,
        "robust_scale": 0.002223900000000084
      },
      "width": {
        "n": 150,
        "median": 0.03216666666666685,
        "mean": 0.033142222222222247,
        "std": 0.0029688123742636135,
        "q25": 0.0306666666666659,
        "q75": 0.035666666666667374,
        "robust_scale": 0.004200699999999877
      },
      "left_width": {
        "n": 150,
        "median": 0.016,
        "mean": 0.015877777777777744,
        "std": 0.0009462727401576496,
        "q25": 0.015333333333333626,
        "q75": 0.0166666666666666,
        "robust_scale": 0.002
      },
      "right_width": {
        "n": 150,
        "median": 0.01616666666666725,
        "mean": 0.01726444444444447,
        "std": 0.0031329306281799203,
        "q25": 0.0140000000000002,
        "q75": 0.0200000000000004,
        "robust_scale": 0.004200699999999285
      },
      "chi2_like_rt_mean": 1.2202816790733917,
      "chi2_like_width_mean": 0.5534184344663625,
      "status_top": {
        "matched_c18_rule": 72,
        "matched_c18_rule_baseexpand": 55,
        "matched_c18_rule_valley_baseexpand": 12,
        "matched_c18_rule_valley": 10,
        "matched_c18_local_bounds_valley": 1
      }
    },
    "C18:3N3": {
      "rt": {
        "n": 150,
        "median": 7.644,
        "mean": 7.644148888888888,
        "std": 0.002403249857285518,
        "q25": 7.642666666666667,
        "q75": 7.645333333333333,
        "robust_scale": 0.001976799999999782
      },
      "width": {
        "n": 150,
        "median": 0.0466666666666668,
        "mean": 0.04311777777777776,
        "std": 0.01320842249064427,
        "q25": 0.0419999999999998,
        "q75": 0.0486666666666666,
        "robust_scale": 0.004447799999999479
      },
      "left_width": {
        "n": 150,
        "median": 0.0083333333333337,
        "mean": 0.00941111111111104,
        "std": 0.0028737423443531617,
        "q25": 0.008,
        "q75": 0.009000000000000074,
        "robust_scale": 0.0028737423443531617
      },
      "right_width": {
        "n": 150,
        "median": 0.0383333333333339,
        "mean": 0.03370666666666667,
        "std": 0.011959061030897892,
        "q25": 0.0279999999999995,
        "q75": 0.04024999999999983,
        "robust_scale": 0.0042007000000005455
      },
      "chi2_like_rt_mean": 1.4836658500899584,
      "chi2_like_width_mean": 9.45547933634475,
      "status_top": {
        "matched_c18_rule": 115,
        "matched_c18_rule_valley": 13,
        "matched_c18_rule_baseexpand": 12,
        "matched_c18_rule_valley_baseexpand": 9,
        "matched_c18_local_bounds_valley_baseexpand": 1
      }
    },
    "C20:4N6": {
      "rt": {
        "n": 150,
        "median": 8.373333333333333,
        "mean": 8.373567668362517,
        "std": 0.0021439422229460993,
        "q25": 8.372,
        "q75": 8.375,
        "robust_scale": 0.001985450826156339
      },
      "width": {
        "n": 150,
        "median": 0.0476666666666663,
        "mean": 0.046900837194204896,
        "std": 0.0032462538137806767,
        "q25": 0.0459999999999993,
        "q75": 0.04866666666666705,
        "robust_scale": 0.0032462538137806767
      },
      "left_width": {
        "n": 150,
        "median": 0.025666666666666,
        "mean": 0.0257565572514054,
        "std": 0.0023169540118449057,
        "q25": 0.0250000000000003,
        "q75": 0.0266666666666655,
        "robust_scale": 0.0023169540118449057
      },
      "right_width": {
        "n": 150,
        "median": 0.0213333333333327,
        "mean": 0.021144279942799448,
        "std": 0.002795419784697275,
        "q25": 0.0196666666666658,
        "q75": 0.0229999999999996,
        "robust_scale": 0.00247100000000035
      },
      "chi2_like_rt_mean": 1.1799552211730922,
      "chi2_like_width_mean": 1.055654361681439,
      "status_top": {
        "matched_c20_rule": 69,
        "matched_c20_local": 52,
        "matched_c20_fit": 28,
        "matched_c20_rule_baseexpand": 1
      }
    },
    "C20:5": {
      "rt": {
        "n": 150,
        "median": 8.404333333333334,
        "mean": 8.404883309187793,
        "std": 0.0034171438744661753,
        "q25": 8.402666666666665,
        "q75": 8.405666666666665,
        "robust_scale": 0.002471000000000386
      },
      "width": {
        "n": 150,
        "median": 0.0328361665027401,
        "mean": 0.03005887822415025,
        "std": 0.009021082470372975,
        "q25": 0.029416666666666598,
        "q75": 0.03607854743352055,
        "robust_scale": 0.0050168751721436575
      },
      "left_width": {
        "n": 150,
        "median": 0.009084241639368551,
        "mean": 0.010502471993590017,
        "std": 0.003522377155859429,
        "q25": 0.0079999999999991,
        "q75": 0.014666666666665,
        "robust_scale": 0.004078496654526973
      },
      "right_width": {
        "n": 150,
        "median": 0.022666666666668597,
        "mean": 0.019556406230560187,
        "std": 0.006647920326138705,
        "q25": 0.018244428969359648,
        "q75": 0.02432779861733795,
        "robust_scale": 0.0029652000000023686
      },
      "chi2_like_rt_mean": 1.9619485177043805,
      "chi2_like_width_mean": 3.5397961755467575,
      "status_top": {
        "matched_c20_rule": 52,
        "matched_c20_local": 33,
        "matched_c20_fit": 28,
        "matched_c20_local_baseexpand": 19,
        "matched_c20_rule_baseexpand": 18
      }
    },
    "C20:3N8": {
      "rt": {
        "n": 150,
        "median": 8.459770595249925,
        "mean": 8.4600331195553,
        "std": 0.002132027191709842,
        "q25": 8.458333333333334,
        "q75": 8.461333333333334,
        "robust_scale": 0.0021308845175374764
      },
      "width": {
        "n": 150,
        "median": 0.0556666666666672,
        "mean": 0.05829197576086543,
        "std": 0.007171335658118258,
        "q25": 0.0546666666666659,
        "q75": 0.05700000000000165,
        "robust_scale": 0.007171335658118258
      },
      "left_width": {
        "n": 150,
        "median": 0.032,
        "mean": 0.03127118191472185,
        "std": 0.003359648817349543,
        "q25": 0.0280000000000004,
        "q75": 0.0330000000000012,
        "robust_scale": 0.0024709999999990846
      },
      "right_width": {
        "n": 150,
        "median": 0.0236666666666671,
        "mean": 0.027020793846143518,
        "std": 0.00676880635990112,
        "q25": 0.0220000000000002,
        "q75": 0.0280000000000004,
        "robust_scale": 0.0039536000000008654
      },
      "chi2_like_rt_mean": 1.0162509385361183,
      "chi2_like_width_mean": 1.1340172756642342,
      "status_top": {
        "matched_c20_rule": 55,
        "matched_c20_local": 33,
        "matched_c20_fit": 28,
        "matched_c20_local_baseexpand": 19,
        "matched_c20_rule_baseexpand": 15
      }
    },
    "C22:6": {
      "rt": {
        "n": 150,
        "median": 9.238333333333332,
        "mean": 9.23874729605362,
        "std": 0.002270906442090938,
        "q25": 9.237333333333334,
        "q75": 9.239916666666668,
        "robust_scale": 0.0019768000000050493
      },
      "width": {
        "n": 150,
        "median": 0.0443333333333306,
        "mean": 0.04342888888888874,
        "std": 0.003812520633419141,
        "q25": 0.04208333333333322,
        "q75": 0.0443333333333342,
        "robust_scale": 0.003812520633419141
      },
      "left_width": {
        "n": 150,
        "median": 0.0278143542992754,
        "mean": 0.025969518275842648,
        "std": 0.003961188667707169,
        "q25": 0.0226666666666659,
        "q75": 0.0279999999999986,
        "robust_scale": 0.003961188667707169
      },
      "right_width": {
        "n": 150,
        "median": 0.0166666666666657,
        "mean": 0.017459370613046036,
        "std": 0.002163565008249241,
        "q25": 0.0163333333333337,
        "q75": 0.0190000000000001,
        "robust_scale": 0.002163565008249241
      },
      "chi2_like_rt_mean": 1.363546091176309,
      "chi2_like_width_mean": 1.0562780946255905,
      "status_top": {
        "matched_c22_rule_tailtight_baseexpand": 51,
        "matched_c22_rule": 35,
        "matched_c22_rule_baseexpand": 33,
        "matched_c22_pvfit_tail_baseexpand": 15,
        "matched_c22_rule_tailtight": 9
      }
    },
    "C22:5": {
      "rt": {
        "n": 149,
        "median": 9.271666666666668,
        "mean": 9.27171216983073,
        "std": 0.002718542509257091,
        "q25": 9.270333333333332,
        "q75": 9.273,
        "robust_scale": 0.0019767999999971485
      },
      "width": {
        "n": 150,
        "median": 0.0313333333333343,
        "mean": 0.027822222222222064,
        "std": 0.006304926547187583,
        "q25": 0.019083333333334423,
        "q75": 0.0316666666666662,
        "robust_scale": 0.006304926547187583
      },
      "left_width": {
        "n": 149,
        "median": 0.0161153623168193,
        "mean": 0.014121565803885084,
        "std": 0.0034103378044496977,
        "q25": 0.009666666666666,
        "q75": 0.0163333333333337,
        "robust_scale": 0.0034103378044496977
      },
      "right_width": {
        "n": 149,
        "median": 0.0150000000000005,
        "mean": 0.0136099778202758,
        "std": 0.003463827636570091,
        "q25": 0.009666666666666,
        "q75": 0.0153333333333343,
        "robust_scale": 0.003463827636570091
      },
      "chi2_like_rt_mean": 1.8917704970430371,
      "chi2_like_width_mean": 1.3101195060748947,
      "status_top": {
        "matched_c22_rule": 49,
        "matched_c22_rule_tailtight_baseexpand": 46,
        "matched_c22_rule_baseexpand": 18,
        "matched_c22_pvfit_tail_baseexpand": 16,
        "matched_c22_rule_tailtight": 14
      }
    },
    "C22:4": {
      "rt": {
        "n": 150,
        "median": 9.301666666666666,
        "mean": 9.301906209023851,
        "std": 0.0021681237202022105,
        "q25": 9.300666666666668,
        "q75": 9.303333333333336,
        "robust_scale": 0.0019767999999971485
      },
      "width": {
        "n": 150,
        "median": 0.0403333333333346,
        "mean": 0.040693333333333116,
        "std": 0.0026078286696733354,
        "q25": 0.0396666666666654,
        "q75": 0.0419999999999998,
        "robust_scale": 0.0026078286696733354
      },
      "left_width": {
        "n": 150,
        "median": 0.0153333333333325,
        "mean": 0.015246209023850165,
        "std": 0.0010002881843614044,
        "q25": 0.0150000000000005,
        "q75": 0.0155299557460013,
        "robust_scale": 0.002
      },
      "right_width": {
        "n": 150,
        "median": 0.0253333333333323,
        "mean": 0.02544712430948291,
        "std": 0.002292354698354252,
        "q25": 0.024333333333333252,
        "q75": 0.0263333333333335,
        "robust_scale": 0.002292354698354252
      },
      "chi2_like_rt_mean": 1.2176201973556062,
      "chi2_like_width_mean": 1.0190566646042887,
      "status_top": {
        "matched_c22_rule_tailtight_baseexpand": 52,
        "matched_c22_rule": 41,
        "matched_c22_rule_baseexpand": 27,
        "matched_c22_pvfit_tail": 16,
        "matched_c22_rule_tailtight": 8
      }
    }
  }
}